pyvigi/__init__.py
pyvigi/base.py
pyvigi/buttons.py
pyvigi/controls.py
pyvigi/display.py
pyvigi/theme.py
pyvigi-0.0.3.dist-info/LICENCE
pyvigi-0.0.3.dist-info/METADATA
pyvigi-0.0.3.dist-info/WHEEL
pyvigi-0.0.3.dist-info/top_level.txt
pyvigi-0.0.3.dist-info/RECORD
